biotools/__init__.py
biotools/main.py
biotools/uniprotkb.py
src/__init__.py
src/main.py
src/uniprotkb.py
biotools_cli-0.1.8.dist-info/LICENSE
biotools_cli-0.1.8.dist-info/METADATA
biotools_cli-0.1.8.dist-info/WHEEL
biotools_cli-0.1.8.dist-info/entry_points.txt
biotools_cli-0.1.8.dist-info/top_level.txt
biotools_cli-0.1.8.dist-info/RECORD
