Metadata-Version: 2.1
Name: biotools-cli
Version: 0.1.8
Summary: Command line interface for Bioinformatics.
Home-page: https://gitee.com/siogian/biotools-cli.git
Author: Liang Xiaojian
Author-email: wakeam@outlook.com
License: UNKNOWN
Project-URL: Bug Tracker, https://gitee.com/siogian/biotools-cli/issues
Platform: UNKNOWN
Classifier: Programming Language :: Python :: 3
Classifier: License :: OSI Approved :: MIT License
Classifier: Operating System :: OS Independent
Requires-Python: >=3.8
License-File: LICENSE
Requires-Dist: Click
Requires-Dist: pandas
Requires-Dist: InquirerPy
Requires-Dist: biopython
Requires-Dist: tqdm
Requires-Dist: thefuzz
